Metadata-Version: 1.1
Name: nb2py
Version: 0.1.6
Summary: Dumps marked code cells from a Jupyter notebook into a text file.
Home-page: https://github.com/HugoGuillen/nb2py
Author: Hugo Guillen-Ramirez
Author-email: hugoagr@gmail.com
License: MIT
Download-URL: https://github.com/HugoGuillen/nb2py/archive/0.1.6.tar.gz
Keywords: jupyter
Platform: UNKNOWN
